{
  "photos": [
    {
      "name": "Anna Khosh Kaka",
      "photo_image_url": "https://www.barnorama.com/wp-content/uploads/2020/01/Sexy-Hot-Girl-Selfies-1.jpg",
      "owner": "IDK",
      "id": 5
    },
    {
      "name": "Anna Khosh Kaka",
      "photo_image_url": "https://www.barnorama.com/wp-content/uploads/2020/01/Sexy-Hot-Girl-Selfies-1.jpg",
      "owner": "IDK",
      "id": 6
    },
    {
      "name": "Anna Khosh Kaka",
      "photo_image_url": "https://www.barnorama.com/wp-content/uploads/2020/01/Sexy-Hot-Girl-Selfies-1.jpg",
      "owner": "IDK",
      "id": 7
    },
    {
      "name": "Anna Khosh Kaka",
      "photo_image_url": "https://www.barnorama.com/wp-content/uploads/2020/01/Sexy-Hot-Girl-Selfies-1.jpg",
      "owner": "IDK",
      "id": 8
    }
  ]
}